ipypong/__init__.py
ipypong-0.1.0.dist-info/licenses/LICENSE
ipypong-0.1.0.dist-info/METADATA
ipypong-0.1.0.dist-info/WHEEL
ipypong-0.1.0.dist-info/top_level.txt
ipypong-0.1.0.dist-info/RECORD
