Metadata-Version: 2.4
Name: ipypong
Version: 0.1.0
Summary: Play pong in Jupyter Notebooks.
Home-page: https://github.com/haesleinhuepf/ipypong
Author: Robert Haase
Author-email: robert.haase@uni-leipzig.de
License: BSD-3-Clause
Project-URL: Bug Tracker, https://github.com/haesleinhuepf/ipypong/issues
Project-URL: Documentation, https://github.com/haesleinhuepf/ipypong#README.md
Project-URL: Source Code, https://github.com/haesleinhuepf/ipypong
Project-URL: User Support, https://github.com/haesleinhuepf/ipypong/issues
Classifier: Development Status :: 2 - Pre-Alpha
Classifier: Intended Audience :: Developers
Classifier: License :: OSI Approved :: BSD License
Classifier: Operating System :: OS Independent
Classifier: Programming Language :: Python
Classifier: Programming Language :: Python :: 3
Classifier: Programming Language :: Python :: 3.9
Classifier: Programming Language :: Python :: 3.10
Classifier: Programming Language :: Python :: 3.11
Classifier: Topic :: Scientific/Engineering :: Image Processing
Requires-Python: >=3.9
License-File: LICENSE
Requires-Dist: ipycanvas
Requires-Dist: ipywidgets
Requires-Dist: ipyevents
Provides-Extra: testing
Requires-Dist: tox; extra == "testing"
Requires-Dist: pytest; extra == "testing"
Requires-Dist: pytest-cov; extra == "testing"
Dynamic: license-file
